{
  "project_info": {
    "project_number": "649453449387",
    "project_id": "chat-app-86fe5",
    "storage_bucket": "chat-app-86fe5.appspot.com"
  },
  "client": [
    {
      "client_info": {
        "mobilesdk_app_id": "1:649453449387:android:fbd743a5b71008a3c707ee",
        "android_client_info": {
          "package_name": "com.example.chat_firebase"
        }
      },
      "oauth_client": [],
      "api_key": [
        {
          "current_key": "AIzaSyCHXRRKN1l0Nw69YIWqtylB3cgjPmewJhc"
        }
      ],
      "services": {
        "appinvite_service": {
          "other_platform_oauth_client": []
        }
      }
    }
  ],
  "configuration_version": "1"
}